propka/__init__.py
propka/__main__.py
propka/_version.py
propka/atom.py
propka/bonds.py
propka/calculations.py
propka/conformation_container.py
propka/coupled_groups.py
propka/determinant.py
propka/determinants.py
propka/energy.py
propka/group.py
propka/hybrid36.py
propka/hydrogens.py
propka/input.py
propka/iterative.py
propka/lib.py
propka/ligand.py
propka/ligand_pka_values.py
propka/molecular_container.py
propka/output.py
propka/parameters.py
propka/propka.cfg
propka/protein_bonds.json
propka/protonate.py
propka/run.py
propka/vector_algebra.py
propka/version.py
tests/__init__.py
tests/test_basic_regression.py
tests/test_hybrid36.py
tests/test_protonate.py
tests/test_run.py
tests/test_streamio.py
tests/test_version.py
propka-3.5.0.dist-info/LICENSE
propka-3.5.0.dist-info/METADATA
propka-3.5.0.dist-info/WHEEL
propka-3.5.0.dist-info/entry_points.txt
propka-3.5.0.dist-info/top_level.txt
propka-3.5.0.dist-info/zip-safe
propka-3.5.0.dist-info/RECORD
