Metadata-Version: 2.1
Name: propka
Version: 3.5.0
Summary: Heuristic pKa calculations with ligands
Home-page: http://propka.org
Author: Jan H. Jensen
Author-email: jhjensen@chem.ku.dk
Maintainer: Nathan Baker
Maintainer-email: nathanandrewbaker@gmail.com
License: LGPL v2.1
Keywords: science
Classifier: Development Status :: 6 - Mature
Classifier: Environment :: Console
Classifier: Intended Audience :: Science/Research
Classifier: License :: OSI Approved :: GNU Lesser General Public License v2 (LGPLv2)
Classifier: Operating System :: POSIX
Classifier: Operating System :: MacOS :: MacOS X
Classifier: Operating System :: Microsoft :: Windows
Classifier: Programming Language :: Python
Classifier: Programming Language :: Python :: 3.8
Classifier: Programming Language :: Python :: 3.9
Classifier: Programming Language :: Python :: 3.10
Classifier: Programming Language :: Python :: 3.11
Classifier: Topic :: Scientific/Engineering :: Bio-Informatics
Classifier: Topic :: Scientific/Engineering :: Chemistry
Requires-Python: >=3.8
License-File: LICENSE
